project/__init__.py
project/src/__init__.py
project/src/app.py
project/src/config.py
project/src/data.py
project/src/engine.py
project/src/model.py
project/src/predict.py
project/src/train.py
project/src/utils.py
py_fresh-0.1.1.dist-info/LICENSE
py_fresh-0.1.1.dist-info/METADATA
py_fresh-0.1.1.dist-info/WHEEL
py_fresh-0.1.1.dist-info/entry_points.txt
py_fresh-0.1.1.dist-info/top_level.txt
py_fresh-0.1.1.dist-info/RECORD
