Metadata-Version: 2.1
Name: py-fresh
Version: 0.1.1
Summary: A Packager for Python Projects
Home-page: https://github.com/oke-aditya/py_fresh/tree/master/
Author: Aditya Oke
Author-email: okeaditya315@gmail.com
License: MIT License
Keywords: Template,Python
Platform: UNKNOWN
Classifier: Development Status :: 3 - Alpha
Classifier: Intended Audience :: Developers
Classifier: License :: OSI Approved :: MIT License
Classifier: Natural Language :: English
Classifier: Programming Language :: Python :: 3.6
Classifier: Programming Language :: Python :: 3.7
Classifier: Programming Language :: Python :: 3.8
Requires-Python: >=3.6
Requires-Dist: flask
